{
    "structures":[
        {
            "name": "Altar",
            "update": "cursed_worlds"
        },{
            "name": "Animal Pen",
            "update": "original",
            "tag": ["animal"]
        },{
            "name": "Apple Tree",
            "update": "original",
            "tag": ["source", "shiny"]
        },{
            "name": "Burner Generator",
            "update": "cities",
            "tag": ["power"]
        },{
            "name": "Cathedral",
            "update": "island"
        },{
            "name": "Farm",
            "update": "original",
            "tag": ["farming"]
        },{
            "name": "Pirate Boat",
            "update": "island"
        }
    ],
    "villagers":[
        {
            "name": "City Advisor",
            "update": "cities",
            "tag": ["npc", "cities"]
        },{
            "name": "Villager",
            "update": "original"
        }
    ],
    "resources":[
        {
            "name": "10 \"dollar\"",
            "image-id": "ten_dollar",
            "update": "cities",
            "tag": ["currency"]
        },{
            "name": "Artwork",
            "update": "cities"
        },{
            "name": "Bone",
            "update": "original"
        }
    ],
    "ideas":[
        {
            "name": "Idea: Altar",
            "update": "cursed_worlds"
        }
    ],
    "food":[
        {
            "name": "Apple",
            "update": "original",
            "tag": ["farming"]
        }
    ],
    "mobs":[
        {
            "name": "Bear",
            "update": "original",
            "tag": ["melee"]
        }
    ],
    "locations":[
        {
            "name": "Catacombs",
            "update": "original"
        }
    ],
    "rumors":[
        {
            "name": "Rumor: Combat",
            "update": "original"
        }
    ],
    "equipment":[
        {
            "name": "Axe",
            "update": "cursed_worlds",
            "tag": ["melee"]
        },{
            "name": "Blowpipe",
            "update": "cursed_worlds",
            "tag": ["ranged"]
        },{
            "name": "Bone Staff",
            "update": "cursed_worlds",
            "tag": ["magic"]
        },{
            "name": "Chainmail Armor",
            "update": "cursed_worlds",
            "tag": ["chest"]
        },{
            "name": "Dark Amulet",
            "update": "cursed_worlds",
            "tag": ["head"]
        }
    ],
    "spirits-n-curses":[
        {
            "name": "Curse of Death",
            "update": "cursed_worlds"
        }
    ],
    "weather":[
        {
            "name": "Lightning",
            "update": "cities"
        }
    ],
    "disasters":[
        {
            "name": "Drought",
            "update": "cities"
        }
    ],
    "landmarks":[
        {
            "name": "Academy",
            "update": "cities"
        }
    ],
    "booster-packs":[
        {
            "name": "Humble Beginnings",
            "image-id": "pack_humble_beginnings",
            "update": "original",
            "tag": ["mainland"]
        },{
            "name": "Wild Weather",
            "image-id": "pack_wild_weather",
            "update": "cities",
            "tag": ["cities"]
        }
    ]
}